pydocsearch.py
pydocsearch-1.0.3.dist-info/METADATA
pydocsearch-1.0.3.dist-info/WHEEL
pydocsearch-1.0.3.dist-info/entry_points.txt
pydocsearch-1.0.3.dist-info/top_level.txt
pydocsearch-1.0.3.dist-info/RECORD
